configfacets/__init__.py
configfacets/base_http.py
configfacets/configuration.py
configfacets/dict.py
configfacets-0.0.5.dist-info/LICENSE
configfacets-0.0.5.dist-info/METADATA
configfacets-0.0.5.dist-info/WHEEL
configfacets-0.0.5.dist-info/top_level.txt
configfacets-0.0.5.dist-info/RECORD
