Metadata-Version: 2.1
Name: configfacets
Version: 0.0.5
Summary: Package for generating application configuration
Home-page: https://github.com/configfacets/python
Author: Gokul Nathan
Author-email: nathangokul111@gmail.com
Classifier: Programming Language :: Python :: 3
Classifier: License :: OSI Approved :: MIT License
Classifier: Operating System :: OS Independent
Requires-Python: >=3.6
License-File: LICENSE
Requires-Dist: requests
Requires-Dist: pyyaml
